runenv/__about__.py
runenv/__init__.py
runenv/api.py
runenv/cli.py
runenv/legacy.py
runenv/parser.py
runenv/py.typed
runenv-1.3.0.dist-info/METADATA
runenv-1.3.0.dist-info/WHEEL
runenv-1.3.0.dist-info/entry_points.txt
runenv-1.3.0.dist-info/licenses/AUTHORS.md
runenv-1.3.0.dist-info/licenses/LICENSE
runenv-1.3.0.dist-info/RECORD
