Metadata-Version: 2.4
Name: runenv
Version: 1.3.0
Project-URL: Documentation, https://github.com/onjin/runenv#readme
Project-URL: Issues, https://github.com/onjin/runenv/issues
Project-URL: Source, https://github.com/onjin/runenv
Author-email: Marek Wywiał <onjinx@gmail.com>
License-Expression: MIT
License-File: AUTHORS.md
License-File: LICENSE
Classifier: Development Status :: 4 - Beta
Classifier: Programming Language :: Python
Classifier: Programming Language :: Python :: 3.7
Classifier: Programming Language :: Python :: 3.8
Classifier: Programming Language :: Python :: 3.9
Classifier: Programming Language :: Python :: 3.10
Classifier: Programming Language :: Python :: 3.11
Classifier: Programming Language :: Python :: 3.12
Classifier: Programming Language :: Python :: 3.13
Classifier: Programming Language :: Python :: Implementation :: CPython
Classifier: Programming Language :: Python :: Implementation :: PyPy
Requires-Python: >=3.7
Provides-Extra: devel
Requires-Dist: coverage[toml]; extra == 'devel'
Requires-Dist: mkchangelog; extra == 'devel'
Requires-Dist: mkdocs; extra == 'devel'
Requires-Dist: mkdocs-material; extra == 'devel'
Requires-Dist: mypy; extra == 'devel'
Requires-Dist: pytest; extra == 'devel'
Requires-Dist: pytest-cov; extra == 'devel'
Requires-Dist: ruff==0.11.12; extra == 'devel'
Provides-Extra: devel-docs
Requires-Dist: mkdocs; extra == 'devel-docs'
Requires-Dist: mkdocs-material; extra == 'devel-docs'
Provides-Extra: devel-test
Requires-Dist: coverage[toml]; extra == 'devel-test'
Requires-Dist: pytest; extra == 'devel-test'
Requires-Dist: pytest-cov; extra == 'devel-test'
Provides-Extra: devel-types
Requires-Dist: mypy; extra == 'devel-types'
Provides-Extra: toml
Requires-Dist: tomli; (python_version < '3.11') and extra == 'toml'
Provides-Extra: yaml
Requires-Dist: pyyaml; extra == 'yaml'
